{
"meta":{"test_sets":[],"test_metrics":[],"learn_metrics":[{"best_value":"Min","name":"RMSE"}],"launch_mode":"Train","parameters":"","iteration_count":300,"learn_sets":["learn"],"name":"experiment"},
"iterations":[
{"learn":[1.08764155],"iteration":0,"passed_time":0.1452947902,"remaining_time":43.44314227},
{"learn":[1.042547628],"iteration":1,"passed_time":0.1532783691,"remaining_time":22.838477},
{"learn":[1.002594631],"iteration":2,"passed_time":0.156892171,"remaining_time":15.53232493},
{"learn":[0.9698642902],"iteration":3,"passed_time":0.1606743634,"remaining_time":11.88990289},
{"learn":[0.9399442144],"iteration":4,"passed_time":0.1648822029,"remaining_time":9.728049973},
{"learn":[0.9131131117],"iteration":5,"passed_time":0.1685898082,"remaining_time":8.260900602},
{"learn":[0.891045275],"iteration":6,"passed_time":0.1721042467,"remaining_time":7.203792041},
{"learn":[0.8714811777],"iteration":7,"passed_time":0.1755925283,"remaining_time":6.409127282},
{"learn":[0.8562003379],"iteration":8,"passed_time":0.1793459502,"remaining_time":5.798852391},
{"learn":[0.8403727126],"iteration":9,"passed_time":0.183086319,"remaining_time":5.309503252},
{"learn":[0.8275363504],"iteration":10,"passed_time":0.1864974557,"remaining_time":4.899796789},
{"learn":[0.816709863],"iteration":11,"passed_time":0.1900610718,"remaining_time":4.561465723},
{"learn":[0.8083852557],"iteration":12,"passed_time":0.1935316056,"remaining_time":4.27258237},
{"learn":[0.7982286556],"iteration":13,"passed_time":0.1975432797,"remaining_time":4.035527},
{"learn":[0.7910840008],"iteration":14,"passed_time":0.2011464473,"remaining_time":3.821782499},
{"learn":[0.7854286787],"iteration":15,"passed_time":0.2045971692,"remaining_time":3.631599753},
{"learn":[0.7794079064],"iteration":16,"passed_time":0.2081039382,"remaining_time":3.464318501},
{"learn":[0.7727313537],"iteration":17,"passed_time":0.212054557,"remaining_time":3.32218806},
{"learn":[0.7692571223],"iteration":18,"passed_time":0.215483909,"remaining_time":3.186893601},
{"learn":[0.766059291],"iteration":19,"passed_time":0.2190625824,"remaining_time":3.066876153},
{"learn":[0.7640563095],"iteration":20,"passed_time":0.2212205594,"remaining_time":2.939073146},
{"learn":[0.7606431693],"iteration":21,"passed_time":0.2247188668,"remaining_time":2.839629317},
{"learn":[0.7569847969],"iteration":22,"passed_time":0.2289762066,"remaining_time":2.757669967},
{"learn":[0.7549020382],"iteration":23,"passed_time":0.2322619829,"remaining_time":2.671012803},
{"learn":[0.7516262748],"iteration":24,"passed_time":0.2359331952,"remaining_time":2.595265148},
{"learn":[0.7500519239],"iteration":25,"passed_time":0.2392924729,"remaining_time":2.521774522},
{"learn":[0.748287609],"iteration":26,"passed_time":0.2429078705,"remaining_time":2.456068468},
{"learn":[0.7462665483],"iteration":27,"passed_time":0.2465869898,"remaining_time":2.395416472},
{"learn":[0.7434896027],"iteration":28,"passed_time":0.2501834692,"remaining_time":2.337921385},
{"learn":[0.7413897355],"iteration":29,"passed_time":0.2536735735,"remaining_time":2.283062161},
{"learn":[0.7397034057],"iteration":30,"passed_time":0.25716402,"remaining_time":2.231520044},
{"learn":[0.7388938817],"iteration":31,"passed_time":0.2608284736,"remaining_time":2.184438466},
{"learn":[0.7379657248],"iteration":32,"passed_time":0.2640881485,"remaining_time":2.136713201},
{"learn":[0.7373209178],"iteration":33,"passed_time":0.2673758371,"remaining_time":2.091822726},
{"learn":[0.7361914803],"iteration":34,"passed_time":0.2708085938,"remaining_time":2.050407925},
{"learn":[0.735233604],"iteration":35,"passed_time":0.2743572202,"remaining_time":2.011952948},
{"learn":[0.7335008226],"iteration":36,"passed_time":0.2783507924,"remaining_time":1.978547524},
{"learn":[0.7322048815],"iteration":37,"passed_time":0.2816981869,"remaining_time":1.942234867},
{"learn":[0.7309187193],"iteration":38,"passed_time":0.285187138,"remaining_time":1.908560077},
{"learn":[0.7303340093],"iteration":39,"passed_time":0.2884448726,"remaining_time":1.874891672},
{"learn":[0.7299621926],"iteration":40,"passed_time":0.2922056436,"remaining_time":1.845884432},
{"learn":[0.7288516275],"iteration":41,"passed_time":0.2957805932,"remaining_time":1.81693793},
{"learn":[0.7279889995],"iteration":42,"passed_time":0.2991493101,"remaining_time":1.7879389},
{"learn":[0.7277964621],"iteration":43,"passed_time":0.3010190782,"remaining_time":1.751383728},
{"learn":[0.7273235701],"iteration":44,"passed_time":0.3043690988,"remaining_time":1.724758227},
{"learn":[0.7265306192],"iteration":45,"passed_time":0.3079521268,"remaining_time":1.700431309},
{"learn":[0.7261012929],"iteration":46,"passed_time":0.3113533665,"remaining_time":1.676008547},
{"learn":[0.7255900214],"iteration":47,"passed_time":0.314737725,"remaining_time":1.652373056},
{"learn":[0.7251535238],"iteration":48,"passed_time":0.3178928068,"remaining_time":1.628389684},
{"learn":[0.7246782611],"iteration":49,"passed_time":0.3210989057,"remaining_time":1.605494529},
{"learn":[0.7240526003],"iteration":50,"passed_time":0.3248611074,"remaining_time":1.586086583},
{"learn":[0.7237590746],"iteration":51,"passed_time":0.328036235,"remaining_time":1.564480506},
{"learn":[0.7233693919],"iteration":52,"passed_time":0.3313399085,"remaining_time":1.544169007},
{"learn":[0.7229320909],"iteration":53,"passed_time":0.3346364006,"remaining_time":1.524454714},
{"learn":[0.7224127755],"iteration":54,"passed_time":0.3380450924,"remaining_time":1.50583723},
{"learn":[0.7220676647],"iteration":55,"passed_time":0.3417353602,"remaining_time":1.488989784},
{"learn":[0.7217122529],"iteration":56,"passed_time":0.3450220033,"remaining_time":1.470883277},
{"learn":[0.7212674976],"iteration":57,"passed_time":0.3482750652,"remaining_time":1.453147686},
{"learn":[0.7202386975],"iteration":58,"passed_time":0.351525887,"remaining_time":1.435893877},
{"learn":[0.719399897],"iteration":59,"passed_time":0.3549546374,"remaining_time":1.419818549},
{"learn":[0.7189187511],"iteration":60,"passed_time":0.358601134,"remaining_time":1.405011},
{"learn":[0.7183353398],"iteration":61,"passed_time":0.362006257,"remaining_time":1.389636922},
{"learn":[0.7180009038],"iteration":62,"passed_time":0.3652856874,"remaining_time":1.374169967},
{"learn":[0.7177056694],"iteration":63,"passed_time":0.3685548248,"remaining_time":1.359045916},
{"learn":[0.7173202356],"iteration":64,"passed_time":0.3719042734,"remaining_time":1.344576989},
{"learn":[0.7166625449],"iteration":65,"passed_time":0.3756800265,"remaining_time":1.331956458},
{"learn":[0.7155148718],"iteration":66,"passed_time":0.3791984672,"remaining_time":1.318705117},
{"learn":[0.7151582279],"iteration":67,"passed_time":0.3824337381,"remaining_time":1.30477393},
{"learn":[0.7148530467],"iteration":68,"passed_time":0.3858033803,"remaining_time":1.291602621},
{"learn":[0.7143793972],"iteration":69,"passed_time":0.3896462852,"remaining_time":1.280266366},
{"learn":[0.7138590759],"iteration":70,"passed_time":0.3933628188,"remaining_time":1.268733599},
{"learn":[0.7135984254],"iteration":71,"passed_time":0.396993637,"remaining_time":1.257146517},
{"learn":[0.7127510218],"iteration":72,"passed_time":0.4005538489,"remaining_time":1.245557859},
{"learn":[0.7125246172],"iteration":73,"passed_time":0.4040599119,"remaining_time":1.234020812},
{"learn":[0.712319951],"iteration":74,"passed_time":0.4077691074,"remaining_time":1.223307322},
{"learn":[0.7120966665],"iteration":75,"passed_time":0.4110642276,"remaining_time":1.211557724},
{"learn":[0.7118343997],"iteration":76,"passed_time":0.4143128028,"remaining_time":1.199892922},
{"learn":[0.7114624979],"iteration":77,"passed_time":0.4175901999,"remaining_time":1.188525954},
{"learn":[0.7110254409],"iteration":78,"passed_time":0.4212113723,"remaining_time":1.178325485},
{"learn":[0.71030389],"iteration":79,"passed_time":0.4245845778,"remaining_time":1.167607589},
{"learn":[0.7098439183],"iteration":80,"passed_time":0.4279454128,"remaining_time":1.157037598},
{"learn":[0.7087471629],"iteration":81,"passed_time":0.4312068357,"remaining_time":1.146379148},
{"learn":[0.708220449],"iteration":82,"passed_time":0.4346786078,"remaining_time":1.13644889},
{"learn":[0.707082258],"iteration":83,"passed_time":0.4385945775,"remaining_time":1.127814628},
{"learn":[0.7064523437],"iteration":84,"passed_time":0.4419859505,"remaining_time":1.117964463},
{"learn":[0.705914736],"iteration":85,"passed_time":0.4452102835,"remaining_time":1.107848845},
{"learn":[0.7057247046],"iteration":86,"passed_time":0.4484676471,"remaining_time":1.097972515},
{"learn":[0.7054448654],"iteration":87,"passed_time":0.4520858971,"remaining_time":1.089116025},
{"learn":[0.7047265831],"iteration":88,"passed_time":0.4558825619,"remaining_time":1.080800231},
{"learn":[0.7043654129],"iteration":89,"passed_time":0.4591886843,"remaining_time":1.071440263},
{"learn":[0.7038453027],"iteration":90,"passed_time":0.4625466552,"remaining_time":1.062332428},
{"learn":[0.7029891353],"iteration":91,"passed_time":0.4658078419,"remaining_time":1.053130773},
{"learn":[0.7024582821],"iteration":92,"passed_time":0.4695813461,"remaining_time":1.04519719},
{"learn":[0.7018773107],"iteration":93,"passed_time":0.4730140267,"remaining_time":1.036605208},
{"learn":[0.7011343257],"iteration":94,"passed_time":0.4764459648,"remaining_time":1.02812024},
{"learn":[0.7006112482],"iteration":95,"passed_time":0.4799399965,"remaining_time":1.019872493},
{"learn":[0.700022757],"iteration":96,"passed_time":0.4834079251,"remaining_time":1.011668132},
{"learn":[0.6995985767],"iteration":97,"passed_time":0.4870865294,"remaining_time":1.003994683},
{"learn":[0.6992664941],"iteration":98,"passed_time":0.4903397577,"remaining_time":0.9955382959},
{"learn":[0.6989517204],"iteration":99,"passed_time":0.4937360959,"remaining_time":0.9874721919},
{"learn":[0.6983363703],"iteration":100,"passed_time":0.4971579931,"remaining_time":0.9795489172},
{"learn":[0.6978789384],"iteration":101,"passed_time":0.5006509515,"remaining_time":0.971851847},
{"learn":[0.6970727102],"iteration":102,"passed_time":0.5044330732,"remaining_time":0.9647894701},
{"learn":[0.6965266798],"iteration":103,"passed_time":0.5078623582,"remaining_time":0.9571252135},
{"learn":[0.6956877985],"iteration":104,"passed_time":0.5114909849,"remaining_time":0.9499118292},
{"learn":[0.6947903931],"iteration":105,"passed_time":0.5150543654,"remaining_time":0.9426466688},
{"learn":[0.6940396803],"iteration":106,"passed_time":0.5191415605,"remaining_time":0.9363955251},
{"learn":[0.6933332357],"iteration":107,"passed_time":0.5225695005,"remaining_time":0.9290124454},
{"learn":[0.6927760565],"iteration":108,"passed_time":0.5260327783,"remaining_time":0.9217638592},
{"learn":[0.6922933444],"iteration":109,"passed_time":0.5296219615,"remaining_time":0.9148015699},
{"learn":[0.6914329288],"iteration":110,"passed_time":0.5336360208,"remaining_time":0.9086234948},
{"learn":[0.6909035393],"iteration":111,"passed_time":0.5370417988,"remaining_time":0.9014630194},
{"learn":[0.6903152572],"iteration":112,"passed_time":0.5404646408,"remaining_time":0.8943972374},
{"learn":[0.6893500198],"iteration":113,"passed_time":0.5439597381,"remaining_time":0.887513257},
{"learn":[0.6887697365],"iteration":114,"passed_time":0.5473075615,"remaining_time":0.8804512946},
{"learn":[0.6883228273],"iteration":115,"passed_time":0.5510912124,"remaining_time":0.8741446817},
{"learn":[0.6875054998],"iteration":116,"passed_time":0.5545804442,"remaining_time":0.8674206948},
{"learn":[0.6868902245],"iteration":117,"passed_time":0.5581759442,"remaining_time":0.8609154393},
{"learn":[0.6863041198],"iteration":118,"passed_time":0.5615196249,"remaining_time":0.8540760682},
{"learn":[0.685551932],"iteration":119,"passed_time":0.5654742842,"remaining_time":0.8482114264},
{"learn":[0.6850670123],"iteration":120,"passed_time":0.568884641,"remaining_time":0.8415731466},
{"learn":[0.6844003779],"iteration":121,"passed_time":0.5723263343,"remaining_time":0.8350335041},
{"learn":[0.6835440416],"iteration":122,"passed_time":0.5757791294,"remaining_time":0.8285602107},
{"learn":[0.682654291],"iteration":123,"passed_time":0.5792029537,"remaining_time":0.8220945149},
{"learn":[0.6821173197],"iteration":124,"passed_time":0.5831033224,"remaining_time":0.8163446514},
{"learn":[0.6814913663],"iteration":125,"passed_time":0.5865308153,"remaining_time":0.8099711259},
{"learn":[0.6807330592],"iteration":126,"passed_time":0.5900235252,"remaining_time":0.8037328336},
{"learn":[0.6802360156],"iteration":127,"passed_time":0.593381301,"remaining_time":0.7973561233},
{"learn":[0.6795370805],"iteration":128,"passed_time":0.597065434,"remaining_time":0.7914588311},
{"learn":[0.67896811],"iteration":129,"passed_time":0.6006114322,"remaining_time":0.7854149498},
{"learn":[0.6784084312],"iteration":130,"passed_time":0.6041004585,"remaining_time":0.7793357061},
{"learn":[0.6778258301],"iteration":131,"passed_time":0.6075854179,"remaining_time":0.7732905319},
{"learn":[0.6772004465],"iteration":132,"passed_time":0.6109898513,"remaining_time":0.7671827456},
{"learn":[0.6768645],"iteration":133,"passed_time":0.6148052489,"remaining_time":0.7616244128},
{"learn":[0.6761834005],"iteration":134,"passed_time":0.6184164528,"remaining_time":0.7558423312},
{"learn":[0.6755472445],"iteration":135,"passed_time":0.6218807424,"remaining_time":0.7499150129},
{"learn":[0.674716026],"iteration":136,"passed_time":0.6252435925,"remaining_time":0.7439029604},
{"learn":[0.6740574317],"iteration":137,"passed_time":0.6289219985,"remaining_time":0.7382997373},
{"learn":[0.6733716989],"iteration":138,"passed_time":0.6324629307,"remaining_time":0.7325649773},
{"learn":[0.6729133316],"iteration":139,"passed_time":0.6359032744,"remaining_time":0.7267465993},
{"learn":[0.6724759333],"iteration":140,"passed_time":0.6391955341,"remaining_time":0.720794964},
{"learn":[0.6720997721],"iteration":141,"passed_time":0.6426284462,"remaining_time":0.7150372853},
{"learn":[0.6715045031],"iteration":142,"passed_time":0.6465908151,"remaining_time":0.7098934124},
{"learn":[0.6708541952],"iteration":143,"passed_time":0.6501140694,"remaining_time":0.7042902418},
{"learn":[0.6705165118],"iteration":144,"passed_time":0.6534433464,"remaining_time":0.6985084048},
{"learn":[0.6695192635],"iteration":145,"passed_time":0.6569291709,"remaining_time":0.6929252898},
{"learn":[0.668655689],"iteration":146,"passed_time":0.660559221,"remaining_time":0.6875208219},
{"learn":[0.668016811],"iteration":147,"passed_time":0.6643734107,"remaining_time":0.6823294489},
{"learn":[0.667684087],"iteration":148,"passed_time":0.6678013726,"remaining_time":0.6767651494},
{"learn":[0.6672330745],"iteration":149,"passed_time":0.6711399969,"remaining_time":0.6711399969},
{"learn":[0.6665989486],"iteration":150,"passed_time":0.6746555971,"remaining_time":0.6657197614},
{"learn":[0.6663356876],"iteration":151,"passed_time":0.6782402631,"remaining_time":0.6603918352},
{"learn":[0.6660420353],"iteration":152,"passed_time":0.681722197,"remaining_time":0.6549879932},
{"learn":[0.665489839],"iteration":153,"passed_time":0.6851003837,"remaining_time":0.6495107534},
{"learn":[0.6649393514],"iteration":154,"passed_time":0.6885812023,"remaining_time":0.6441566086},
{"learn":[0.6645602539],"iteration":155,"passed_time":0.6920131349,"remaining_time":0.6387813553},
{"learn":[0.6640485078],"iteration":156,"passed_time":0.6960790609,"remaining_time":0.6340083166},
{"learn":[0.663891396],"iteration":157,"passed_time":0.6993625523,"remaining_time":0.628541028},
{"learn":[0.6633059193],"iteration":158,"passed_time":0.7028473138,"remaining_time":0.6232796934},
{"learn":[0.6629817267],"iteration":159,"passed_time":0.7061723617,"remaining_time":0.6179008165},
{"learn":[0.6624116585],"iteration":160,"passed_time":0.7099241365,"remaining_time":0.6129158694},
{"learn":[0.6622369366],"iteration":161,"passed_time":0.7133652422,"remaining_time":0.6076815026},
{"learn":[0.6618900654],"iteration":162,"passed_time":0.7168073128,"remaining_time":0.60246995},
{"learn":[0.6613486218],"iteration":163,"passed_time":0.7203164788,"remaining_time":0.5973356166},
{"learn":[0.6609930906],"iteration":164,"passed_time":0.7236833037,"remaining_time":0.5921045212},
{"learn":[0.6606043644],"iteration":165,"passed_time":0.7277046259,"remaining_time":0.5874242161},
{"learn":[0.6602984765],"iteration":166,"passed_time":0.731108145,"remaining_time":0.5822597802},
{"learn":[0.660101013],"iteration":167,"passed_time":0.7343660519,"remaining_time":0.5770018979},
{"learn":[0.659429144],"iteration":168,"passed_time":0.7377957139,"remaining_time":0.5719008196},
{"learn":[0.6588117444],"iteration":169,"passed_time":0.7414448987,"remaining_time":0.5669872755},
{"learn":[0.6583598445],"iteration":170,"passed_time":0.7450362036,"remaining_time":0.5620448554},
{"learn":[0.6580400402],"iteration":171,"passed_time":0.7484239016,"remaining_time":0.5569666245},
{"learn":[0.657719076],"iteration":172,"passed_time":0.7518509287,"remaining_time":0.5519368089},
{"learn":[0.6574548285],"iteration":173,"passed_time":0.7551784952,"remaining_time":0.5468533931},
{"learn":[0.6570826213],"iteration":174,"passed_time":0.759666912,"remaining_time":0.5426192229},
{"learn":[0.6567047492],"iteration":175,"passed_time":0.7635468102,"remaining_time":0.5379534344},
{"learn":[0.656171369],"iteration":176,"passed_time":0.7672729854,"remaining_time":0.5331897017},
{"learn":[0.6555466467],"iteration":177,"passed_time":0.7712225659,"remaining_time":0.5285907474},
{"learn":[0.6551023243],"iteration":178,"passed_time":0.775909021,"remaining_time":0.5244971594},
{"learn":[0.6546387246],"iteration":179,"passed_time":0.7809861264,"remaining_time":0.5206574176},
{"learn":[0.6542717568],"iteration":180,"passed_time":0.7849833804,"remaining_time":0.5160940457},
{"learn":[0.6537934366],"iteration":181,"passed_time":0.7889684427,"remaining_time":0.5115289904},
{"learn":[0.6533630117],"iteration":182,"passed_time":0.7927478475,"remaining_time":0.5068387878},
{"learn":[0.6530099733],"iteration":183,"passed_time":0.7961981423,"remaining_time":0.5019510028},
{"learn":[0.652727867],"iteration":184,"passed_time":0.7995666117,"remaining_time":0.4970278938},
{"learn":[0.6525206572],"iteration":185,"passed_time":0.8029094743,"remaining_time":0.4921058068},
{"learn":[0.6520875152],"iteration":186,"passed_time":0.8064589972,"remaining_time":0.4873254903},
{"learn":[0.6517814867],"iteration":187,"passed_time":0.8102294094,"remaining_time":0.4826898609},
{"learn":[0.6513290512],"iteration":188,"passed_time":0.8136256984,"remaining_time":0.4778436641},
{"learn":[0.6507853174],"iteration":189,"passed_time":0.8172223984,"remaining_time":0.473128757},
{"learn":[0.6504354152],"iteration":190,"passed_time":0.8207219693,"remaining_time":0.4683701291},
{"learn":[0.6499567241],"iteration":191,"passed_time":0.8248338501,"remaining_time":0.4639690407},
{"learn":[0.6495402963],"iteration":192,"passed_time":0.8282999614,"remaining_time":0.459212932},
{"learn":[0.6492638582],"iteration":193,"passed_time":0.8324077693,"remaining_time":0.4548207399},
{"learn":[0.6489132448],"iteration":194,"passed_time":0.8359522653,"remaining_time":0.4501281429},
{"learn":[0.6485439069],"iteration":195,"passed_time":0.8399722694,"remaining_time":0.4456995715},
{"learn":[0.6482974618],"iteration":196,"passed_time":0.8433874807,"remaining_time":0.4409589366},
{"learn":[0.6479571806],"iteration":197,"passed_time":0.8469216683,"remaining_time":0.4362929806},
{"learn":[0.6475473974],"iteration":198,"passed_time":0.851151528,"remaining_time":0.4319914791},
{"learn":[0.6472366438],"iteration":199,"passed_time":0.855272973,"remaining_time":0.4276364865},
{"learn":[0.6466882587],"iteration":200,"passed_time":0.8592813937,"remaining_time":0.4232281491},
{"learn":[0.6463568658],"iteration":201,"passed_time":0.8630358731,"remaining_time":0.4187005721},
{"learn":[0.6461587823],"iteration":202,"passed_time":0.8667268405,"remaining_time":0.4141502637},
{"learn":[0.6457402863],"iteration":203,"passed_time":0.8711440034,"remaining_time":0.4099501192},
{"learn":[0.6453579548],"iteration":204,"passed_time":0.8750736393,"remaining_time":0.4055219304},
{"learn":[0.6450267825],"iteration":205,"passed_time":0.8787059789,"remaining_time":0.4009629224},
{"learn":[0.6445805099],"iteration":206,"passed_time":0.8826474464,"remaining_time":0.3965517513},
{"learn":[0.6442740148],"iteration":207,"passed_time":0.8868063148,"remaining_time":0.3922412546},
{"learn":[0.6441393571],"iteration":208,"passed_time":0.8904923743,"remaining_time":0.3877263448},
{"learn":[0.6437903555],"iteration":209,"passed_time":0.8942595213,"remaining_time":0.3832540805},
{"learn":[0.6435849257],"iteration":210,"passed_time":0.8979838675,"remaining_time":0.3787704465},
{"learn":[0.6433824229],"iteration":211,"passed_time":0.9015260167,"remaining_time":0.3742183465},
{"learn":[0.6429677497],"iteration":212,"passed_time":0.9054792822,"remaining_time":0.3698436505},
{"learn":[0.6426585355],"iteration":213,"passed_time":0.9092036307,"remaining_time":0.3653808983},
{"learn":[0.6424043584],"iteration":214,"passed_time":0.9128254002,"remaining_time":0.3608844605},
{"learn":[0.6420784839],"iteration":215,"passed_time":0.9165070153,"remaining_time":0.3564193948},
{"learn":[0.6417650048],"iteration":216,"passed_time":0.9207945294,"remaining_time":0.3521932993},
{"learn":[0.6414152188],"iteration":217,"passed_time":0.9245932056,"remaining_time":0.3477827654},
{"learn":[0.6412324062],"iteration":218,"passed_time":0.9284518351,"remaining_time":0.3433999938},
{"learn":[0.6409049812],"iteration":219,"passed_time":0.9322646337,"remaining_time":0.3390053213},
{"learn":[0.6406327077],"iteration":220,"passed_time":0.9367083095,"remaining_time":0.3348414319},
{"learn":[0.6403498751],"iteration":221,"passed_time":0.9406718539,"remaining_time":0.330506327},
{"learn":[0.6398657181],"iteration":222,"passed_time":0.9445994985,"remaining_time":0.3261621587},
{"learn":[0.6397284602],"iteration":223,"passed_time":0.9481883376,"remaining_time":0.3217067574},
{"learn":[0.6395367553],"iteration":224,"passed_time":0.9526150752,"remaining_time":0.3175383584},
{"learn":[0.6390060257],"iteration":225,"passed_time":0.9566761307,"remaining_time":0.3132479366},
{"learn":[0.6385410979],"iteration":226,"passed_time":0.960602572,"remaining_time":0.3089162456},
{"learn":[0.6382527966],"iteration":227,"passed_time":0.964269861,"remaining_time":0.3045062719},
{"learn":[0.6378904307],"iteration":228,"passed_time":0.9686328153,"remaining_time":0.3003184711},
{"learn":[0.6375856158],"iteration":229,"passed_time":0.9726140742,"remaining_time":0.2960129791},
{"learn":[0.6373773196],"iteration":230,"passed_time":0.9763278868,"remaining_time":0.2916304077},
{"learn":[0.6370791219],"iteration":231,"passed_time":0.9802404376,"remaining_time":0.2873118524},
{"learn":[0.6368452918],"iteration":232,"passed_time":0.9845292457,"remaining_time":0.2831049762},
{"learn":[0.6362894639],"iteration":233,"passed_time":0.9890238283,"remaining_time":0.2789554388},
{"learn":[0.6359737214],"iteration":234,"passed_time":0.9928703326,"remaining_time":0.274623709},
{"learn":[0.6355153309],"iteration":235,"passed_time":0.996806896,"remaining_time":0.2703205142},
{"learn":[0.6352391698],"iteration":236,"passed_time":1.001178225,"remaining_time":0.2661359838},
{"learn":[0.6349630448],"iteration":237,"passed_time":1.005022554,"remaining_time":0.261812598},
{"learn":[0.6346385055],"iteration":238,"passed_time":1.008894633,"remaining_time":0.2575003039},
{"learn":[0.6344482968],"iteration":239,"passed_time":1.012816004,"remaining_time":0.253204001},
{"learn":[0.6341772117],"iteration":240,"passed_time":1.017482074,"remaining_time":0.2490931219},
{"learn":[0.6339993363],"iteration":241,"passed_time":1.021332965,"remaining_time":0.244782281},
{"learn":[0.6334071924],"iteration":242,"passed_time":1.025203632,"remaining_time":0.2404798642},
{"learn":[0.6328423457],"iteration":243,"passed_time":1.028820511,"remaining_time":0.2361227402},
{"learn":[0.6323493244],"iteration":244,"passed_time":1.032938157,"remaining_time":0.2318840762},
{"learn":[0.6320123955],"iteration":245,"passed_time":1.036597168,"remaining_time":0.2275457197},
{"learn":[0.6316542552],"iteration":246,"passed_time":1.040178499,"remaining_time":0.2231961961},
{"learn":[0.6314013696],"iteration":247,"passed_time":1.043757428,"remaining_time":0.2188523639},
{"learn":[0.6312532302],"iteration":248,"passed_time":1.047939859,"remaining_time":0.2146382844},
{"learn":[0.6310059548],"iteration":249,"passed_time":1.051198246,"remaining_time":0.2102396493},
{"learn":[0.6307953127],"iteration":250,"passed_time":1.054502334,"remaining_time":0.2058590213},
{"learn":[0.6304248657],"iteration":251,"passed_time":1.057976966,"remaining_time":0.2015194221},
{"learn":[0.6299509413],"iteration":252,"passed_time":1.061510561,"remaining_time":0.1971976141},
{"learn":[0.6296397131],"iteration":253,"passed_time":1.065232439,"remaining_time":0.1929161109},
{"learn":[0.6293672561],"iteration":254,"passed_time":1.068459498,"remaining_time":0.1885516762},
{"learn":[0.6292234791],"iteration":255,"passed_time":1.071670332,"remaining_time":0.1841933384},
{"learn":[0.6290199395],"iteration":256,"passed_time":1.075005715,"remaining_time":0.1798647694},
{"learn":[0.628700849],"iteration":257,"passed_time":1.078486895,"remaining_time":0.175567634},
{"learn":[0.6282233173],"iteration":258,"passed_time":1.08221889,"remaining_time":0.1713165039},
{"learn":[0.6278719621],"iteration":259,"passed_time":1.085938332,"remaining_time":0.1670674357},
{"learn":[0.6275518805],"iteration":260,"passed_time":1.089402615,"remaining_time":0.1627842989},
{"learn":[0.6271773791],"iteration":261,"passed_time":1.093062094,"remaining_time":0.1585357235},
{"learn":[0.6269152351],"iteration":262,"passed_time":1.097120346,"remaining_time":0.1543477292},
{"learn":[0.6267349807],"iteration":263,"passed_time":1.100574989,"remaining_time":0.1500784075},
{"learn":[0.626601742],"iteration":264,"passed_time":1.10394164,"remaining_time":0.1458036129},
{"learn":[0.6261714766],"iteration":265,"passed_time":1.107587052,"remaining_time":0.1415712773},
{"learn":[0.626059774],"iteration":266,"passed_time":1.111431752,"remaining_time":0.1373679694},
{"learn":[0.6257662007],"iteration":267,"passed_time":1.114879725,"remaining_time":0.1331199671},
{"learn":[0.6253585858],"iteration":268,"passed_time":1.118387534,"remaining_time":0.1288848088},
{"learn":[0.6249610353],"iteration":269,"passed_time":1.121861118,"remaining_time":0.1246512353},
{"learn":[0.6245652106],"iteration":270,"passed_time":1.125269185,"remaining_time":0.1204162596},
{"learn":[0.6240716928],"iteration":271,"passed_time":1.12917743,"remaining_time":0.116238853},
{"learn":[0.6237277129],"iteration":272,"passed_time":1.132758322,"remaining_time":0.1120310429},
{"learn":[0.623490457],"iteration":273,"passed_time":1.136242241,"remaining_time":0.1078186068},
{"learn":[0.6231864554],"iteration":274,"passed_time":1.139792146,"remaining_time":0.1036174678},
{"learn":[0.6230230696],"iteration":275,"passed_time":1.143658133,"remaining_time":0.0994485333},
{"learn":[0.6227226555],"iteration":276,"passed_time":1.147199887,"remaining_time":0.09525486426},
{"learn":[0.6223312295],"iteration":277,"passed_time":1.150789488,"remaining_time":0.09106967169},
{"learn":[0.6221642429],"iteration":278,"passed_time":1.154217548,"remaining_time":0.08687658964},
{"learn":[0.6219786823],"iteration":279,"passed_time":1.157642047,"remaining_time":0.08268871763},
{"learn":[0.6217477137],"iteration":280,"passed_time":1.161340212,"remaining_time":0.07852478299},
{"learn":[0.6213629399],"iteration":281,"passed_time":1.164799857,"remaining_time":0.07434892702},
{"learn":[0.6212177319],"iteration":282,"passed_time":1.168353246,"remaining_time":0.07018376392},
{"learn":[0.620919274],"iteration":283,"passed_time":1.172284352,"remaining_time":0.06604418886},
{"learn":[0.6206739325],"iteration":284,"passed_time":1.176689402,"remaining_time":0.06193102115},
{"learn":[0.6203214293],"iteration":285,"passed_time":1.180315106,"remaining_time":0.05777766251},
{"learn":[0.6201141449],"iteration":286,"passed_time":1.183606624,"remaining_time":0.05361284361},
{"learn":[0.6198466573],"iteration":287,"passed_time":1.187080494,"remaining_time":0.04946168725},
{"learn":[0.619341624],"iteration":288,"passed_time":1.190904782,"remaining_time":0.04532855573},
{"learn":[0.6191085824],"iteration":289,"passed_time":1.194451962,"remaining_time":0.04118799868},
{"learn":[0.6187683016],"iteration":290,"passed_time":1.19795878,"remaining_time":0.03705027156},
{"learn":[0.6184636783],"iteration":291,"passed_time":1.201726358,"remaining_time":0.03292400982},
{"learn":[0.6181238938],"iteration":292,"passed_time":1.205178084,"remaining_time":0.02879265048},
{"learn":[0.6177685239],"iteration":293,"passed_time":1.208925294,"remaining_time":0.02467194478},
{"learn":[0.6174373141],"iteration":294,"passed_time":1.212352092,"remaining_time":0.02054834054},
{"learn":[0.6171034951],"iteration":295,"passed_time":1.215740939,"remaining_time":0.01642893161},
{"learn":[0.6168036161],"iteration":296,"passed_time":1.219219107,"remaining_time":0.01231534452},
{"learn":[0.6163638207],"iteration":297,"passed_time":1.222888885,"remaining_time":0.008207307953},
{"learn":[0.6161190154],"iteration":298,"passed_time":1.226347099,"remaining_time":0.004101495313},
{"learn":[0.6159208754],"iteration":299,"passed_time":1.229775698,"remaining_time":0}
]}